[
  {
    "@context": "https://schema.org",
    "@type": "ItemList",
    "itemListElement": [
      {
        "@type": "ListItem",
        "position": 1,
        "item": {
          "@type": "Product",
          "image": "https://i.etsystatic.com/20641892/r/il/f6838b/5515803391/il_fullxfull.5515803391_sjew.jpg",
          "name": "Size Upgrade: Small to Medium/Large",
          "url": "https://www.etsy.com/listing/1586319476/size-upgrade-small-to-mediumlarge",
          "brand": {
            "@type": "Brand",
            "name": "FalkelDesign"
          },
          "offers": {
            "@type": "Offer",
            "price": "15.00",
            "priceCurrency": "USD",
            "availability": "https://schema.org/InStock",
            "priceSpecification": {
              "@type": "UnitPriceSpecification",
              "priceType": "https://schema.org/ListPrice",
              "price": "30.00",
              "priceCurrency": "USD"
            }
          }
        }
      },
      {
        "@type": "ListItem",
        "position": 2,
        "item": {
          "@type": "Product",
          "image": "https://i.etsystatic.com/20641892/r/il/36a3aa/4359639556/il_fullxfull.4359639556_huvp.jpg",
          "name": "Personalized Merry Christmas Doormat: Coconut Fiber Welcome Mat",
          "url": "https://www.etsy.com/listing/1349810947/personalized-merry-christmas-doormat",
          "brand": {
            "@type": "Brand",
            "name": "FalkelDesign"
          },
          "offers": {
            "@type": "Offer",
            "price": "20.30",
            "priceCurrency": "USD",
            "availability": "https://schema.org/InStock",
            "priceSpecification": {
              "@type": "UnitPriceSpecification",
              "priceType": "https://schema.org/ListPrice",
              "price": "29.00",
              "priceCurrency": "USD"
            }
          }
        }
      },
      {
        "@type": "ListItem",
        "position": 3,
        "item": {
          "@type": "Product",
          "image": "https://i.etsystatic.com/20641892/r/il/cd422a/4407008475/il_fullxfull.4407008475_e4nx.jpg",
          "name": "Hi Bye Dog Doormat: Personalized Coconut Welcome Mat",
          "url": "https://www.etsy.com/listing/1335826484/hi-bye-dog-doormat-personalized-coconut",
          "brand": {
            "@type": "Brand",
            "name": "FalkelDesign"
          },
          "offers": {
            "@type": "Offer",
            "price": "20.30",
            "priceCurrency": "USD",
            "availability": "https://schema.org/InStock",
            "priceSpecification": {
              "@type": "UnitPriceSpecification",
              "priceType": "https://schema.org/ListPrice",
              "price": "29.00",
              "priceCurrency": "USD"
            }
          }
        }
      },
      {
        "@type": "ListItem",
        "position": 4,
        "item": {
          "@type": "Product",
          "image": "https://i.etsystatic.com/20641892/r/il/8438dd/4359600916/il_fullxfull.4359600916_43td.jpg",
          "name": "Cat Doormat | Christmas Gift | Housewarming Gift | Welcome Door Mat | Personalized Custom Doormat | Wedding Gift | Personalized Gift",
          "url": "https://www.etsy.com/listing/1335820816/cat-doormat-christmas-gift-housewarming",
          "brand": {
            "@type": "Brand",
            "name": "FalkelDesign"
          },
          "offers": {
            "@type": "Offer",
            "price": "20.30",
            "priceCurrency": "USD",
            "availability": "https://schema.org/InStock",
            "priceSpecification": {
              "@type": "UnitPriceSpecification",
              "priceType": "https://schema.org/ListPrice",
              "price": "29.00",
              "priceCurrency": "USD"
            }
          }
        }
      },
      {
        "@type": "ListItem",
        "position": 5,
        "item": {
          "@type": "Product",
          "image": "https://i.etsystatic.com/20641892/r/il/383218/3834125867/il_fullxfull.3834125867_saxp.jpg",
          "name": "Personalized Coconut Doormat: New Home Gift, Welcome Mat",
          "url": "https://www.etsy.com/listing/1209519801/personalized-coconut-doormat-new-home",
          "brand": {
            "@type": "Brand",
            "name": "FalkelDesign"
          },
          "offers": {
            "@type": "Offer",
            "price": "20.30",
            "priceCurrency": "USD",
            "availability": "https://schema.org/InStock",
            "priceSpecification": {
              "@type": "UnitPriceSpecification",
              "priceType": "https://schema.org/ListPrice",
              "price": "29.00",
              "priceCurrency": "USD"
            }
          }
        }
      },
      {
        "@type": "ListItem",
        "position": 6,
        "item": {
          "@type": "Product",
          "image": "https://i.etsystatic.com/20641892/r/il/73ad7e/3833761055/il_fullxfull.3833761055_htg9.jpg",
          "name": "Shoes Off Doormat | Wedding Gift | Personalized Custom Doormat | Welcome Door Mat | Personalized Gift | Housewarming Gift | New Home Gift",
          "url": "https://www.etsy.com/listing/1195459370/shoes-off-doormat-wedding-gift",
          "brand": {
            "@type": "Brand",
            "name": "FalkelDesign"
          },
          "offers": {
            "@type": "Offer",
            "price": "20.30",
            "priceCurrency": "USD",
            "availability": "https://schema.org/InStock",
            "priceSpecification": {
              "@type": "UnitPriceSpecification",
              "priceType": "https://schema.org/ListPrice",
              "price": "29.00",
              "priceCurrency": "USD"
            }
          }
        }
      },
      {
        "@type": "ListItem",
        "position": 7,
        "item": {
          "@type": "Product",
          "image": "https://i.etsystatic.com/20641892/r/il/04fd90/3786101520/il_fullxfull.3786101520_p6yf.jpg",
          "name": "Did You Call First Doormat | New Home Gift | Housewarming Gift | Wedding Gift | Welcome Door Mat | Custom Doormat | Personalized Gift",
          "url": "https://www.etsy.com/listing/1209399051/did-you-call-first-doormat-new-home-gift",
          "brand": {
            "@type": "Brand",
            "name": "FalkelDesign"
          },
          "offers": {
            "@type": "Offer",
            "price": "20.30",
            "priceCurrency": "USD",
            "availability": "https://schema.org/InStock",
            "priceSpecification": {
              "@type": "UnitPriceSpecification",
              "priceType": "https://schema.org/ListPrice",
              "price": "29.00",
              "priceCurrency": "USD"
            }
          }
        }
      },
      {
        "@type": "ListItem",
        "position": 8,
        "item": {
          "@type": "Product",
          "image": "https://i.etsystatic.com/20641892/r/il/6a2f07/3786031236/il_fullxfull.3786031236_juqc.jpg",
          "name": "Flowers in Jars Doormat: Personalized Coconut Coir Welcome Mat",
          "url": "https://www.etsy.com/listing/1195419820/flowers-in-jars-doormat-personalized",
          "brand": {
            "@type": "Brand",
            "name": "FalkelDesign"
          },
          "offers": {
            "@type": "Offer",
            "price": "20.30",
            "priceCurrency": "USD",
            "availability": "https://schema.org/InStock",
            "priceSpecification": {
              "@type": "UnitPriceSpecification",
              "priceType": "https://schema.org/ListPrice",
              "price": "29.00",
              "priceCurrency": "USD"
            }
          }
        }
      },
      {
        "@type": "ListItem",
        "position": 9,
        "item": {
          "@type": "Product",
          "image": "https://i.etsystatic.com/20641892/r/il/bc0da4/3831875851/il_fullxfull.3831875851_bmwb.jpg",
          "name": "Stay Golden Coconut Doormat: Personalized Welcome Mat",
          "url": "https://www.etsy.com/listing/1208920483/stay-golden-coconut-doormat-personalized",
          "brand": {
            "@type": "Brand",
            "name": "FalkelDesign"
          },
          "offers": {
            "@type": "Offer",
            "price": "20.30",
            "priceCurrency": "USD",
            "availability": "https://schema.org/InStock",
            "priceSpecification": {
              "@type": "UnitPriceSpecification",
              "priceType": "https://schema.org/ListPrice",
              "price": "29.00",
              "priceCurrency": "USD"
            }
          }
        }
      },
      {
        "@type": "ListItem",
        "position": 10,
        "item": {
          "@type": "Product",
          "image": "https://i.etsystatic.com/20641892/r/il/c4d28e/3780928891/il_fullxfull.3780928891_p4nw.jpg",
          "name": "Personalized Coconut Doormat: Welcome Home, Last Name Gift",
          "url": "https://www.etsy.com/listing/1195678793/personalized-coconut-doormat-welcome",
          "brand": {
            "@type": "Brand",
            "name": "FalkelDesign"
          },
          "offers": {
            "@type": "Offer",
            "price": "20.30",
            "priceCurrency": "USD",
            "availability": "https://schema.org/InStock",
            "priceSpecification": {
              "@type": "UnitPriceSpecification",
              "priceType": "https://schema.org/ListPrice",
              "price": "29.00",
              "priceCurrency": "USD"
            }
          }
        }
      },
      {
        "@type": "ListItem",
        "position": 11,
        "item": {
          "@type": "Product",
          "image": "https://i.etsystatic.com/20641892/r/il/862795/3733303002/il_fullxfull.3733303002_itcs.jpg",
          "name": "Personalized Coconut Doormat: New Home Gift, UV Printed",
          "url": "https://www.etsy.com/listing/1181710522/personalized-coconut-doormat-new-home",
          "brand": {
            "@type": "Brand",
            "name": "FalkelDesign"
          },
          "offers": {
            "@type": "Offer",
            "price": "20.30",
            "priceCurrency": "USD",
            "availability": "https://schema.org/InStock",
            "priceSpecification": {
              "@type": "UnitPriceSpecification",
              "priceType": "https://schema.org/ListPrice",
              "price": "29.00",
              "priceCurrency": "USD"
            }
          }
        }
      },
      {
        "@type": "ListItem",
        "position": 12,
        "item": {
          "@type": "Product",
          "image": "https://i.etsystatic.com/20641892/r/il/286d17/3733281086/il_fullxfull.3733281086_kwb4.jpg",
          "name": "Cat Doormat: Personalized Family Name, Coconut Fiber Mat",
          "url": "https://www.etsy.com/listing/1181703930/cat-doormat-personalized-family-name",
          "brand": {
            "@type": "Brand",
            "name": "FalkelDesign"
          },
          "offers": {
            "@type": "Offer",
            "price": "20.30",
            "priceCurrency": "USD",
            "availability": "https://schema.org/InStock",
            "priceSpecification": {
              "@type": "UnitPriceSpecification",
              "priceType": "https://schema.org/ListPrice",
              "price": "29.00",
              "priceCurrency": "USD"
            }
          }
        }
      },
      {
        "@type": "ListItem",
        "position": 13,
        "item": {
          "@type": "Product",
          "image": "https://i.etsystatic.com/20641892/r/il/e49c4e/3780864201/il_fullxfull.3780864201_14kp.jpg",
          "name": "Housewarming Gift | Wedding Gift | New Home Gift | Personalized Custom Doormat | Personalized Gift | Welcome Door Mat | Front Door Decor",
          "url": "https://www.etsy.com/listing/1181703260/housewarming-gift-wedding-gift-new-home",
          "brand": {
            "@type": "Brand",
            "name": "FalkelDesign"
          },
          "offers": {
            "@type": "Offer",
            "price": "20.30",
            "priceCurrency": "USD",
            "availability": "https://schema.org/InStock",
            "priceSpecification": {
              "@type": "UnitPriceSpecification",
              "priceType": "https://schema.org/ListPrice",
              "price": "29.00",
              "priceCurrency": "USD"
            }
          }
        }
      },
      {
        "@type": "ListItem",
        "position": 14,
        "item": {
          "@type": "Product",
          "image": "https://i.etsystatic.com/20641892/r/il/3a52e2/3733167012/il_fullxfull.3733167012_tihk.jpg",
          "name": "Personalized Coconut Doormat: UV Printed Welcome Mat",
          "url": "https://www.etsy.com/listing/1195627997/personalized-coconut-doormat-uv-printed",
          "brand": {
            "@type": "Brand",
            "name": "FalkelDesign"
          },
          "offers": {
            "@type": "Offer",
            "price": "20.30",
            "priceCurrency": "USD",
            "availability": "https://schema.org/InStock",
            "priceSpecification": {
              "@type": "UnitPriceSpecification",
              "priceType": "https://schema.org/ListPrice",
              "price": "29.00",
              "priceCurrency": "USD"
            }
          }
        }
      },
      {
        "@type": "ListItem",
        "position": 15,
        "item": {
          "@type": "Product",
          "image": "https://i.etsystatic.com/20641892/r/il/a25bbc/3776128139/il_fullxfull.3776128139_kn0h.jpg",
          "name": "Hi Bye Cat Doormat: Personalized Coconut Welcome Mat",
          "url": "https://www.etsy.com/listing/1180485032/hi-bye-cat-doormat-personalized-coconut",
          "brand": {
            "@type": "Brand",
            "name": "FalkelDesign"
          },
          "offers": {
            "@type": "Offer",
            "price": "20.30",
            "priceCurrency": "USD",
            "availability": "https://schema.org/InStock",
            "priceSpecification": {
              "@type": "UnitPriceSpecification",
              "priceType": "https://schema.org/ListPrice",
              "price": "29.00",
              "priceCurrency": "USD"
            }
          }
        }
      },
      {
        "@type": "ListItem",
        "position": 16,
        "item": {
          "@type": "Product",
          "image": "https://i.etsystatic.com/20641892/r/il/eb0f5a/3733112738/il_fullxfull.3733112738_j2za.jpg",
          "name": "Floral Coconut Doormat: Personalized Welcome Mat, New Home Gift",
          "url": "https://www.etsy.com/listing/1194438583/floral-coconut-doormat-personalized",
          "brand": {
            "@type": "Brand",
            "name": "FalkelDesign"
          },
          "offers": {
            "@type": "Offer",
            "price": "20.30",
            "priceCurrency": "USD",
            "availability": "https://schema.org/InStock",
            "priceSpecification": {
              "@type": "UnitPriceSpecification",
              "priceType": "https://schema.org/ListPrice",
              "price": "29.00",
              "priceCurrency": "USD"
            }
          }
        }
      },
      {
        "@type": "ListItem",
        "position": 17,
        "item": {
          "@type": "Product",
          "image": "https://i.etsystatic.com/20641892/r/il/7e5a2e/3733117886/il_fullxfull.3733117886_hpej.jpg",
          "name": "Panda Welcome Doormat: Personalized Coconut Fiber Mat",
          "url": "https://www.etsy.com/listing/1194429497/panda-welcome-doormat-personalized",
          "brand": {
            "@type": "Brand",
            "name": "FalkelDesign"
          },
          "offers": {
            "@type": "Offer",
            "price": "20.30",
            "priceCurrency": "USD",
            "availability": "https://schema.org/InStock",
            "priceSpecification": {
              "@type": "UnitPriceSpecification",
              "priceType": "https://schema.org/ListPrice",
              "price": "29.00",
              "priceCurrency": "USD"
            }
          }
        }
      },
      {
        "@type": "ListItem",
        "position": 18,
        "item": {
          "@type": "Product",
          "image": "https://i.etsystatic.com/20641892/r/il/58ac0e/3728491190/il_fullxfull.3728491190_a6fs.jpg",
          "name": "Good Vibes Only Doormat: Personalized Coconut Welcome Mat",
          "url": "https://www.etsy.com/listing/1194424571/good-vibes-only-doormat-personalized",
          "brand": {
            "@type": "Brand",
            "name": "FalkelDesign"
          },
          "offers": {
            "@type": "Offer",
            "price": "20.30",
            "priceCurrency": "USD",
            "availability": "https://schema.org/InStock",
            "priceSpecification": {
              "@type": "UnitPriceSpecification",
              "priceType": "https://schema.org/ListPrice",
              "price": "29.00",
              "priceCurrency": "USD"
            }
          }
        }
      },
      {
        "@type": "ListItem",
        "position": 19,
        "item": {
          "@type": "Product",
          "image": "https://i.etsystatic.com/20641892/r/il/5c27a0/3780717601/il_fullxfull.3780717601_akia.jpg",
          "name": "I Am Blessed Doormat | Housewarming Gift | Welcome Door Mat | New Home Gift | Personalized Custom Doormat | Wedding Gift | Personalized Gift",
          "url": "https://www.etsy.com/listing/1180461942/i-am-blessed-doormat-housewarming-gift",
          "brand": {
            "@type": "Brand",
            "name": "FalkelDesign"
          },
          "offers": {
            "@type": "Offer",
            "price": "20.30",
            "priceCurrency": "USD",
            "availability": "https://schema.org/InStock",
            "priceSpecification": {
              "@type": "UnitPriceSpecification",
              "priceType": "https://schema.org/ListPrice",
              "price": "29.00",
              "priceCurrency": "USD"
            }
          }
        }
      },
      {
        "@type": "ListItem",
        "position": 20,
        "item": {
          "@type": "Product",
          "image": "https://i.etsystatic.com/20641892/r/il/c9a5fb/3673410085/il_fullxfull.3673410085_tiqg.jpg",
          "name": "Wedding Guest Book |  Personalized Wedding Gift| Custom Wood Sign | Home Decor | Wedding Welcome Sign|Custom Wedding Guest Book I Wall Decor",
          "url": "https://www.etsy.com/listing/1167808223/wedding-guest-book-personalized-wedding",
          "brand": {
            "@type": "Brand",
            "name": "FalkelDesign"
          },
          "offers": {
            "@type": "Offer",
            "price": "62.50",
            "priceCurrency": "USD",
            "availability": "https://schema.org/InStock",
            "priceSpecification": {
              "@type": "UnitPriceSpecification",
              "priceType": "https://schema.org/ListPrice",
              "price": "125.00",
              "priceCurrency": "USD"
            }
          }
        }
      },
      {
        "@type": "ListItem",
        "position": 21,
        "item": {
          "@type": "Product",
          "image": "https://i.etsystatic.com/20641892/r/il/603763/3625800400/il_fullxfull.3625800400_fwp3.jpg",
          "name": "Custom Wood Family Name Sign: 3D Wedding Guest Book",
          "url": "https://www.etsy.com/listing/1167807271/custom-wood-family-name-sign-3d-wedding",
          "brand": {
            "@type": "Brand",
            "name": "FalkelDesign"
          },
          "offers": {
            "@type": "Offer",
            "price": "62.50",
            "priceCurrency": "USD",
            "availability": "https://schema.org/InStock",
            "priceSpecification": {
              "@type": "UnitPriceSpecification",
              "priceType": "https://schema.org/ListPrice",
              "price": "125.00",
              "priceCurrency": "USD"
            }
          }
        }
      },
      {
        "@type": "ListItem",
        "position": 22,
        "item": {
          "@type": "Product",
          "image": "https://i.etsystatic.com/20641892/r/il/672e13/3673377561/il_fullxfull.3673377561_h58g.jpg",
          "name": "Custom Wood Wedding Guest Book Sign: Personalized Family Name Decor",
          "url": "https://www.etsy.com/listing/1167801853/custom-wood-wedding-guest-book-sign",
          "brand": {
            "@type": "Brand",
            "name": "FalkelDesign"
          },
          "offers": {
            "@type": "Offer",
            "price": "62.50",
            "priceCurrency": "USD",
            "availability": "https://schema.org/InStock",
            "priceSpecification": {
              "@type": "UnitPriceSpecification",
              "priceType": "https://schema.org/ListPrice",
              "price": "125.00",
              "priceCurrency": "USD"
            }
          }
        }
      },
      {
        "@type": "ListItem",
        "position": 23,
        "item": {
          "@type": "Product",
          "image": "https://i.etsystatic.com/20641892/r/il/65a19c/3673376971/il_fullxfull.3673376971_drej.jpg",
          "name": "Custom Wood Wedding Guest Book Sign: Personalized Family Name Decor",
          "url": "https://www.etsy.com/listing/1153842160/custom-wood-wedding-guest-book-sign",
          "brand": {
            "@type": "Brand",
            "name": "FalkelDesign"
          },
          "offers": {
            "@type": "Offer",
            "price": "62.50",
            "priceCurrency": "USD",
            "availability": "https://schema.org/InStock",
            "priceSpecification": {
              "@type": "UnitPriceSpecification",
              "priceType": "https://schema.org/ListPrice",
              "price": "125.00",
              "priceCurrency": "USD"
            }
          }
        }
      },
      {
        "@type": "ListItem",
        "position": 24,
        "item": {
          "@type": "Product",
          "image": "https://i.etsystatic.com/20641892/r/il/8fc05b/3656267905/il_fullxfull.3656267905_t8bs.jpg",
          "name": "Personalized Wood Name Sign: 3D Laser Cut Couple Gift",
          "url": "https://www.etsy.com/listing/1163356199/personalized-wood-name-sign-3d-laser-cut",
          "brand": {
            "@type": "Brand",
            "name": "FalkelDesign"
          },
          "offers": {
            "@type": "Offer",
            "price": "34.50",
            "priceCurrency": "USD",
            "availability": "https://schema.org/InStock",
            "priceSpecification": {
              "@type": "UnitPriceSpecification",
              "priceType": "https://schema.org/ListPrice",
              "price": "69.00",
              "priceCurrency": "USD"
            }
          }
        }
      },
      {
        "@type": "ListItem",
        "position": 25,
        "item": {
          "@type": "Product",
          "image": "https://i.etsystatic.com/20641892/r/il/eab089/3608421232/il_fullxfull.3608421232_jme1.jpg",
          "name": "Personalized Wood Name Sign: 3D Laser Cut Couple Names",
          "url": "https://www.etsy.com/listing/1163316427/personalized-wood-name-sign-3d-laser-cut",
          "brand": {
            "@type": "Brand",
            "name": "FalkelDesign"
          },
          "offers": {
            "@type": "Offer",
            "price": "34.50",
            "priceCurrency": "USD",
            "availability": "https://schema.org/InStock",
            "priceSpecification": {
              "@type": "UnitPriceSpecification",
              "priceType": "https://schema.org/ListPrice",
              "price": "69.00",
              "priceCurrency": "USD"
            }
          }
        }
      },
      {
        "@type": "ListItem",
        "position": 26,
        "item": {
          "@type": "Product",
          "image": "https://i.etsystatic.com/20641892/r/il/39d66c/3656033763/il_fullxfull.3656033763_tucl.jpg",
          "name": "Personalized Wood Name Sign: 3D Couple Gift, Home Decor (23x3.5 in)",
          "url": "https://www.etsy.com/listing/1163313459/personalized-wood-name-sign-3d-couple",
          "brand": {
            "@type": "Brand",
            "name": "FalkelDesign"
          },
          "offers": {
            "@type": "Offer",
            "price": "34.50",
            "priceCurrency": "USD",
            "availability": "https://schema.org/InStock",
            "priceSpecification": {
              "@type": "UnitPriceSpecification",
              "priceType": "https://schema.org/ListPrice",
              "price": "69.00",
              "priceCurrency": "USD"
            }
          }
        }
      },
      {
        "@type": "ListItem",
        "position": 27,
        "item": {
          "@type": "Product",
          "image": "https://i.etsystatic.com/20641892/r/il/9232d1/2953311437/il_fullxfull.2953311437_cdgq.jpg",
          "name": "Handmade Wooden Headphone & Controller Stand: Teak Oil Finish",
          "url": "https://www.etsy.com/listing/971376143/handmade-wooden-headphone-controller",
          "brand": {
            "@type": "Brand",
            "name": "FalkelDesign"
          },
          "offers": {
            "@type": "Offer",
            "price": "66.50",
            "priceCurrency": "USD",
            "availability": "https://schema.org/InStock"
          }
        }
      },
      {
        "@type": "ListItem",
        "position": 28,
        "item": {
          "@type": "Product",
          "image": "https://i.etsystatic.com/20641892/r/il/0d389e/2953298933/il_fullxfull.2953298933_8ki5.jpg",
          "name": "Handmade Wooden Headphone & Controller Stand: Gamer Gift",
          "url": "https://www.etsy.com/listing/971375911/handmade-wooden-headphone-controller",
          "brand": {
            "@type": "Brand",
            "name": "FalkelDesign"
          },
          "offers": {
            "@type": "Offer",
            "price": "66.50",
            "priceCurrency": "USD",
            "availability": "https://schema.org/InStock"
          }
        }
      },
      {
        "@type": "ListItem",
        "position": 29,
        "item": {
          "@type": "Product",
          "image": "https://i.etsystatic.com/20641892/r/il/daf9c1/2905385494/il_fullxfull.2905385494_li5o.jpg",
          "name": "Wooden Foldable Laptop Stand, Portable Lap Desk, Laptop Bed Tray, Breakfast Serving Tray, Multifunctional Stand, Work From Home Gift for him",
          "url": "https://www.etsy.com/listing/971327093/wooden-foldable-laptop-stand-portable",
          "brand": {
            "@type": "Brand",
            "name": "FalkelDesign"
          },
          "offers": {
            "@type": "Offer",
            "price": "296.00",
            "priceCurrency": "USD",
            "availability": "https://schema.org/InStock"
          }
        }
      },
      {
        "@type": "ListItem",
        "position": 30,
        "item": {
          "@type": "Product",
          "image": "https://i.etsystatic.com/20641892/r/il/912ac3/2873061394/il_fullxfull.2873061394_i190.jpg",
          "name": "Custom Family Name Wood Sign: 3D Laser Cut Pallet Decor",
          "url": "https://www.etsy.com/listing/949187872/custom-family-name-wood-sign-3d-laser",
          "brand": {
            "@type": "Brand",
            "name": "FalkelDesign"
          },
          "offers": {
            "@type": "Offer",
            "price": "39.00",
            "priceCurrency": "USD",
            "availability": "https://schema.org/InStock",
            "priceSpecification": {
              "@type": "UnitPriceSpecification",
              "priceType": "https://schema.org/ListPrice",
              "price": "130.00",
              "priceCurrency": "USD"
            }
          }
        }
      },
      {
        "@type": "ListItem",
        "position": 31,
        "item": {
          "@type": "Product",
          "image": "https://i.etsystatic.com/20641892/r/il/f946b6/2920736723/il_fullxfull.2920736723_f3l7.jpg",
          "name": "Custom Family Name Wood Sign: 3D Laser Cut Pallet Decor",
          "url": "https://www.etsy.com/listing/949187542/custom-family-name-wood-sign-3d-laser",
          "brand": {
            "@type": "Brand",
            "name": "FalkelDesign"
          },
          "offers": {
            "@type": "Offer",
            "price": "39.00",
            "priceCurrency": "USD",
            "availability": "https://schema.org/InStock",
            "priceSpecification": {
              "@type": "UnitPriceSpecification",
              "priceType": "https://schema.org/ListPrice",
              "price": "130.00",
              "priceCurrency": "USD"
            }
          }
        }
      },
      {
        "@type": "ListItem",
        "position": 32,
        "item": {
          "@type": "Product",
          "image": "https://i.etsystatic.com/20641892/r/il/57b521/2873060806/il_fullxfull.2873060806_du0m.jpg",
          "name": "Personalized 3D Wood Family Name Sign: Laser Cut Home Decor",
          "url": "https://www.etsy.com/listing/949185494/personalized-3d-wood-family-name-sign",
          "brand": {
            "@type": "Brand",
            "name": "FalkelDesign"
          },
          "offers": {
            "@type": "Offer",
            "price": "39.00",
            "priceCurrency": "USD",
            "availability": "https://schema.org/InStock",
            "priceSpecification": {
              "@type": "UnitPriceSpecification",
              "priceType": "https://schema.org/ListPrice",
              "price": "130.00",
              "priceCurrency": "USD"
            }
          }
        }
      },
      {
        "@type": "ListItem",
        "position": 33,
        "item": {
          "@type": "Product",
          "image": "https://i.etsystatic.com/20641892/r/il/ec4a14/2920735097/il_fullxfull.2920735097_aao3.jpg",
          "name": "Custom Family Name Wood Sign: 3D Laser Cut Home Decor",
          "url": "https://www.etsy.com/listing/963149133/custom-family-name-wood-sign-3d-laser",
          "brand": {
            "@type": "Brand",
            "name": "FalkelDesign"
          },
          "offers": {
            "@type": "Offer",
            "price": "39.00",
            "priceCurrency": "USD",
            "availability": "https://schema.org/InStock",
            "priceSpecification": {
              "@type": "UnitPriceSpecification",
              "priceType": "https://schema.org/ListPrice",
              "price": "130.00",
              "priceCurrency": "USD"
            }
          }
        }
      },
      {
        "@type": "ListItem",
        "position": 34,
        "item": {
          "@type": "Product",
          "image": "https://i.etsystatic.com/20641892/r/il/d5aa47/3742912928/il_fullxfull.3742912928_mq3y.jpg",
          "name": "Custom Wood Sign | Personalized Family Name Sign | Last Name Sign | Wedding Gift | Home Wall Decor | Anniversary Gift | Custom Wood Signs",
          "url": "https://www.etsy.com/listing/963147161/custom-wood-sign-personalized-family",
          "brand": {
            "@type": "Brand",
            "name": "FalkelDesign"
          },
          "offers": {
            "@type": "Offer",
            "price": "39.00",
            "priceCurrency": "USD",
            "availability": "https://schema.org/InStock",
            "priceSpecification": {
              "@type": "UnitPriceSpecification",
              "priceType": "https://schema.org/ListPrice",
              "price": "130.00",
              "priceCurrency": "USD"
            }
          }
        }
      },
      {
        "@type": "ListItem",
        "position": 35,
        "item": {
          "@type": "Product",
          "image": "https://i.etsystatic.com/20641892/r/il/906815/3856380992/il_fullxfull.3856380992_q5en.jpg",
          "name": "Custom Wood Sign | Family Last Name Sign | Wedding Sign | Established Rustic Decor | Personalized Anniversary & Housewarming Gift",
          "url": "https://www.etsy.com/listing/963134803/custom-wood-sign-family-last-name-sign",
          "brand": {
            "@type": "Brand",
            "name": "FalkelDesign"
          },
          "offers": {
            "@type": "Offer",
            "price": "39.00",
            "priceCurrency": "USD",
            "availability": "https://schema.org/InStock",
            "priceSpecification": {
              "@type": "UnitPriceSpecification",
              "priceType": "https://schema.org/ListPrice",
              "price": "130.00",
              "priceCurrency": "USD"
            }
          }
        }
      }
    ],
    "numberOfItems": 35,
    "url": "https://www.etsy.com/shop/FalkelDesign"
  },
  {
    "@context": "https://schema.org",
    "@type": "ItemList",
    "itemListElement": [
      {
        "@type": "ListItem",
        "position": 1,
        "item": {
          "@type": "Product",
          "image": "https://i.etsystatic.com/13285848/r/il/9ad0cd/7193874062/il_fullxfull.7193874062_7dp4.jpg",
          "name": "Personalized Wooden Valet Tray – Custom Engraved Stackable Desk Organizer",
          "url": "https://www.etsy.com/listing/4368490008/personalized-wooden-valet-tray-custom",
          "brand": {
            "@type": "Brand",
            "name": "Oakywood"
          },
          "offers": {
            "@type": "Offer",
            "price": "297.57",
            "priceCurrency": "BRL",
            "availability": "https://schema.org/InStock"
          }
        }
      },
      {
        "@type": "ListItem",
        "position": 2,
        "item": {
          "@type": "Product",
          "image": "https://i.etsystatic.com/13285848/r/il/d43909/7163776568/il_fullxfull.7163776568_ehrd.jpg",
          "name": "Desk Setup Pro – White Legs - Standing Desk with Shelf and Drawers, Complete Workstation, Home Office Furniture, Ergonomic Desk Organizer",
          "url": "https://www.etsy.com/listing/4362449088/desk-setup-pro-white-legs-standing-desk",
          "brand": {
            "@type": "Brand",
            "name": "Oakywood"
          },
          "offers": {
            "@type": "Offer",
            "price": "12048.58",
            "priceCurrency": "BRL",
            "availability": "https://schema.org/InStock"
          }
        }
      },
      {
        "@type": "ListItem",
        "position": 3,
        "item": {
          "@type": "Product",
          "image": "https://i.etsystatic.com/13285848/r/il/975d68/7163094014/il_fullxfull.7163094014_jgts.jpg",
          "name": "Desk Setup Pro – Black Legs - Standing Desk with Shelf and Drawers, Complete Workstation, Home Office Furniture, Ergonomic Desk Organizer",
          "url": "https://www.etsy.com/listing/4362386192/desk-setup-pro-black-legs-standing-desk",
          "brand": {
            "@type": "Brand",
            "name": "Oakywood"
          },
          "offers": {
            "@type": "Offer",
            "price": "12048.58",
            "priceCurrency": "BRL",
            "availability": "https://schema.org/InStock"
          }
        }
      },
      {
        "@type": "ListItem",
        "position": 4,
        "item": {
          "@type": "Product",
          "image": "https://i.etsystatic.com/13285848/r/il/86c74a/7152777684/il_fullxfull.7152777684_rb8g.jpg",
          "name": "Handmade Solid Wood Table Top: Rustic Modern Desk, Dining, Coffee Table",
          "url": "https://www.etsy.com/listing/4360402259/handmade-solid-wood-table-top-rustic",
          "brand": {
            "@type": "Brand",
            "name": "Oakywood"
          },
          "offers": {
            "@type": "Offer",
            "price": "2423.08",
            "priceCurrency": "BRL",
            "availability": "https://schema.org/InStock"
          }
        }
      },
      {
        "@type": "ListItem",
        "position": 5,
        "item": {
          "@type": "Product",
          "image": "https://i.etsystatic.com/13285848/r/il/adc1e8/6255608327/il_fullxfull.6255608327_56qs.jpg",
          "name": "Solid Oak Floating Shelf Set: Wall Mounted Shelves for Home & Office",
          "url": "https://www.etsy.com/listing/4359807555/solid-oak-floating-shelf-set-wall",
          "brand": {
            "@type": "Brand",
            "name": "Oakywood"
          },
          "offers": {
            "@type": "Offer",
            "price": "2726.72",
            "priceCurrency": "BRL",
            "availability": "https://schema.org/InStock"
          }
        }
      },
      {
        "@type": "ListItem",
        "position": 6,
        "item": {
          "@type": "Product",
          "image": "https://i.etsystatic.com/13285848/r/il/023baa/6792387120/il_fullxfull.6792387120_98kt.jpg",
          "name": "Stackable Wooden Valet Tray Set: Modular Desk Organizer",
          "url": "https://www.etsy.com/listing/4359794596/stackable-wooden-valet-tray-set-modular",
          "brand": {
            "@type": "Brand",
            "name": "Oakywood"
          },
          "offers": {
            "@type": "Offer",
            "price": "661.94",
            "priceCurrency": "BRL",
            "availability": "https://schema.org/InStock"
          }
        }
      },
      {
        "@type": "ListItem",
        "position": 7,
        "item": {
          "@type": "Product",
          "image": "https://i.etsystatic.com/13285848/r/il/60cdae/7149802326/il_fullxfull.7149802326_4ecc.jpg",
          "name": "Oakywood Wooden Catchall Tray Bundle: Minimalist Desk Organizer",
          "url": "https://www.etsy.com/listing/4359792400/oakywood-wooden-catchall-tray-bundle",
          "brand": {
            "@type": "Brand",
            "name": "Oakywood"
          },
          "offers": {
            "@type": "Offer",
            "price": "904.86",
            "priceCurrency": "BRL",
            "availability": "https://schema.org/InStock"
          }
        }
      },
      {
        "@type": "ListItem",
        "position": 8,
        "item": {
          "@type": "Product",
          "image": "https://i.etsystatic.com/13285848/r/il/09c77d/7149717468/il_fullxfull.7149717468_4uvc.jpg",
          "name": "Oakywood Wooden Catchall Tray Mini Bundle: Minimalist Desk Organizer",
          "url": "https://www.etsy.com/listing/4359777536/oakywood-wooden-catchall-tray-mini",
          "brand": {
            "@type": "Brand",
            "name": "Oakywood"
          },
          "offers": {
            "@type": "Offer",
            "price": "479.76",
            "priceCurrency": "BRL",
            "availability": "https://schema.org/InStock"
          }
        }
      },
      {
        "@type": "ListItem",
        "position": 9,
        "item": {
          "@type": "Product",
          "image": "https://i.etsystatic.com/13285848/r/il/c42593/7195143475/il_fullxfull.7195143475_o8rp.jpg",
          "name": "Magnetic Wood Cable Organizer: Desk Cord Management, Tech Gift",
          "url": "https://www.etsy.com/listing/4359296536/magnetic-wood-cable-organizer-desk-cord",
          "brand": {
            "@type": "Brand",
            "name": "Oakywood"
          },
          "offers": {
            "@type": "Offer",
            "price": "236.84",
            "priceCurrency": "BRL",
            "availability": "https://schema.org/InStock"
          }
        }
      },
      {
        "@type": "ListItem",
        "position": 10,
        "item": {
          "@type": "Product",
          "image": "https://i.etsystatic.com/13285848/r/il/55ce84/7250360177/il_fullxfull.7250360177_48h8.jpg",
          "name": "Oakywood Wood Catchall Tray Mini: Minimalist Desk Organizer",
          "url": "https://www.etsy.com/listing/4359162436/oakywood-wood-catchall-tray-mini",
          "brand": {
            "@type": "Brand",
            "name": "Oakywood"
          },
          "offers": {
            "@type": "Offer",
            "price": "176.11",
            "priceCurrency": "BRL",
            "availability": "https://schema.org/InStock"
          }
        }
      },
      {
        "@type": "ListItem",
        "position": 11,
        "item": {
          "@type": "Product",
          "image": "https://i.etsystatic.com/13285848/r/il/8df881/7176308497/il_fullxfull.7176308497_2z9y.jpg",
          "name": "Handmade Solid Wood Standing Desk Pro Mini Bundle - White Legs, Cable Organizer",
          "url": "https://www.etsy.com/listing/4356045979/handmade-solid-wood-standing-desk-pro",
          "brand": {
            "@type": "Brand",
            "name": "Oakywood"
          },
          "offers": {
            "@type": "Offer",
            "price": "8180.16",
            "priceCurrency": "BRL",
            "availability": "https://schema.org/InStock"
          }
        }
      },
      {
        "@type": "ListItem",
        "position": 12,
        "item": {
          "@type": "Product",
          "image": "https://i.etsystatic.com/13285848/r/il/2add0c/7128338754/il_fullxfull.7128338754_tcwm.jpg",
          "name": "Solid Wood Standing Desk Pro Mini Bundle: Black Legs, Cable Organizer",
          "url": "https://www.etsy.com/listing/4356043579/solid-wood-standing-desk-pro-mini-bundle",
          "brand": {
            "@type": "Brand",
            "name": "Oakywood"
          },
          "offers": {
            "@type": "Offer",
            "price": "8180.16",
            "priceCurrency": "BRL",
            "availability": "https://schema.org/InStock"
          }
        }
      },
      {
        "@type": "ListItem",
        "position": 13,
        "item": {
          "@type": "Product",
          "image": "https://i.etsystatic.com/13285848/r/il/0511c5/7176278589/il_fullxfull.7176278589_evnf.jpg",
          "name": "Small Solid Wood Standing Desk: White Legs, Adjustable Height",
          "url": "https://www.etsy.com/listing/4355980173/small-solid-wood-standing-desk-white",
          "brand": {
            "@type": "Brand",
            "name": "Oakywood"
          },
          "offers": {
            "@type": "Offer",
            "price": "7281.38",
            "priceCurrency": "BRL",
            "availability": "https://schema.org/InStock"
          }
        }
      },
      {
        "@type": "ListItem",
        "position": 14,
        "item": {
          "@type": "Product",
          "image": "https://i.etsystatic.com/13285848/r/il/cd13bc/7128250032/il_fullxfull.7128250032_3qdc.jpg",
          "name": "Solid Wood Standing Desk Pro Mini: Black Legs, Height Adjustable  Desk For Small Spaces",
          "url": "https://www.etsy.com/listing/4355972355/solid-wood-standing-desk-pro-mini-black",
          "brand": {
            "@type": "Brand",
            "name": "Oakywood"
          },
          "offers": {
            "@type": "Offer",
            "price": "7281.38",
            "priceCurrency": "BRL",
            "availability": "https://schema.org/InStock"
          }
        }
      },
      {
        "@type": "ListItem",
        "position": 15,
        "item": {
          "@type": "Product",
          "image": "https://i.etsystatic.com/13285848/r/il/2fd745/7392949357/il_fullxfull.7392949357_8ahi.jpg",
          "name": "Solid Oak Desk Shelf Pro: Dual Monitor Stand with Drawer",
          "url": "https://www.etsy.com/listing/4329658744/solid-oak-desk-shelf-pro-dual-monitor",
          "brand": {
            "@type": "Brand",
            "name": "Oakywood"
          },
          "offers": {
            "@type": "Offer",
            "price": "2423.08",
            "priceCurrency": "BRL",
            "availability": "https://schema.org/InStock"
          }
        }
      },
      {
        "@type": "ListItem",
        "position": 16,
        "item": {
          "@type": "Product",
          "image": "https://i.etsystatic.com/13285848/r/il/20f029/7037094275/il_fullxfull.7037094275_4nwh.jpg",
          "name": "Oakywood Desk Shelf Pro: Solid Oak Monitor Stand with Drawer",
          "url": "https://www.etsy.com/listing/4329654103/oakywood-desk-shelf-pro-solid-oak",
          "brand": {
            "@type": "Brand",
            "name": "Oakywood"
          },
          "offers": {
            "@type": "Offer",
            "price": "2423.08",
            "priceCurrency": "BRL",
            "availability": "https://schema.org/InStock"
          }
        }
      },
      {
        "@type": "ListItem",
        "position": 17,
        "item": {
          "@type": "Product",
          "image": "https://i.etsystatic.com/13285848/r/il/fd77fb/6985229637/il_fullxfull.6985229637_709e.jpg",
          "name": "Desk-Mounted Wooden Headphone Hook: Adjustable Steel Clamp",
          "url": "https://www.etsy.com/listing/4319998902/desk-mounted-wooden-headphone-hook",
          "brand": {
            "@type": "Brand",
            "name": "Oakywood"
          },
          "offers": {
            "@type": "Offer",
            "price": "297.57",
            "priceCurrency": "BRL",
            "availability": "https://schema.org/InStock"
          }
        }
      },
      {
        "@type": "ListItem",
        "position": 18,
        "item": {
          "@type": "Product",
          "image": "https://i.etsystatic.com/13285848/r/il/b4eefa/6985000597/il_fullxfull.6985000597_1hqb.jpg",
          "name": "Steel Laptop Mount for Desk Shelf: Ergonomic Adjustable Laptop Stand",
          "url": "https://www.etsy.com/listing/4319954784/steel-laptop-mount-for-desk-shelf",
          "brand": {
            "@type": "Brand",
            "name": "Oakywood"
          },
          "offers": {
            "@type": "Offer",
            "price": "540.49",
            "priceCurrency": "BRL",
            "availability": "https://schema.org/InStock"
          }
        }
      },
      {
        "@type": "ListItem",
        "position": 19,
        "item": {
          "@type": "Product",
          "image": "https://i.etsystatic.com/13285848/r/il/f6bdd9/6979511827/il_fullxfull.6979511827_8u8w.jpg",
          "name": "Wool Felt Desk Organizer: Hanging Tabletop Pocket, Clamp-On Design",
          "url": "https://www.etsy.com/listing/4318916395/wool-felt-desk-organizer-hanging",
          "brand": {
            "@type": "Brand",
            "name": "Oakywood"
          },
          "offers": {
            "@type": "Offer",
            "price": "1208.50",
            "priceCurrency": "BRL",
            "availability": "https://schema.org/InStock"
          }
        }
      },
      {
        "@type": "ListItem",
        "position": 20,
        "item": {
          "@type": "Product",
          "image": "https://i.etsystatic.com/13285848/r/il/0d2ab6/6979452667/il_fullxfull.6979452667_iosl.jpg",
          "name": "Hanging Wool Felt Desk Organizer: Clamp-On Laptop Storage",
          "url": "https://www.etsy.com/listing/4318914999/hanging-wool-felt-desk-organizer-clamp",
          "brand": {
            "@type": "Brand",
            "name": "Oakywood"
          },
          "offers": {
            "@type": "Offer",
            "price": "1208.50",
            "priceCurrency": "BRL",
            "availability": "https://schema.org/InStock"
          }
        }
      },
      {
        "@type": "ListItem",
        "position": 21,
        "item": {
          "@type": "Product",
          "image": "https://i.etsystatic.com/13285848/r/il/792699/6792391154/il_fullxfull.6792391154_gkvd.jpg",
          "name": "Stackable Wooden Valet Tray: Modular Desk Organizer",
          "url": "https://www.etsy.com/listing/1903256973/stackable-wooden-valet-tray-modular-desk",
          "brand": {
            "@type": "Brand",
            "name": "Oakywood"
          },
          "offers": {
            "@type": "Offer",
            "price": "236.84",
            "priceCurrency": "BRL",
            "availability": "https://schema.org/InStock"
          }
        }
      },
      {
        "@type": "ListItem",
        "position": 22,
        "item": {
          "@type": "Product",
          "image": "https://i.etsystatic.com/13285848/r/il/281006/6790577324/il_fullxfull.6790577324_bh55.jpg",
          "name": "Oakywood Desk Shelf Mini: Wooden Monitor Stand with Drawer",
          "url": "https://www.etsy.com/listing/1888697358/oakywood-desk-shelf-mini-wooden-monitor",
          "brand": {
            "@type": "Brand",
            "name": "Oakywood"
          },
          "offers": {
            "@type": "Offer",
            "price": "1512.15",
            "priceCurrency": "BRL",
            "availability": "https://schema.org/InStock"
          }
        }
      },
      {
        "@type": "ListItem",
        "position": 23,
        "item": {
          "@type": "Product",
          "image": "https://i.etsystatic.com/13285848/r/il/38b2e6/6757517860/il_fullxfull.6757517860_4no4.jpg",
          "name": "Magnetic Wood Cable Organizer: Desk Cord Management Solution",
          "url": "https://www.etsy.com/listing/1896268283/magnetic-wood-cable-organizer-desk-cord",
          "brand": {
            "@type": "Brand",
            "name": "Oakywood"
          },
          "offers": {
            "@type": "Offer",
            "price": "236.84",
            "priceCurrency": "BRL",
            "availability": "https://schema.org/InStock"
          }
        }
      },
      {
        "@type": "ListItem",
        "position": 24,
        "item": {
          "@type": "Product",
          "image": "https://i.etsystatic.com/13285848/r/il/50864f/6162906084/il_fullxfull.6162906084_l5s9.jpg",
          "name": "Modular Wooden Desk Drawer: White Steel Base, Desk Organizer - Oakywood Desk Shelf Compatible",
          "url": "https://www.etsy.com/listing/1770945793/modular-wooden-desk-drawer-white-steel",
          "brand": {
            "@type": "Brand",
            "name": "Oakywood"
          },
          "offers": {
            "@type": "Offer",
            "price": "789.47",
            "priceCurrency": "BRL",
            "availability": "https://schema.org/InStock"
          }
        }
      },
      {
        "@type": "ListItem",
        "position": 25,
        "item": {
          "@type": "Product",
          "image": "https://i.etsystatic.com/13285848/r/il/1fd657/2238695445/il_fullxfull.2238695445_jn4y.jpg",
          "name": "Personalized Wooden iPhone & Apple Watch Docking Station: Engraved Gift",
          "url": "https://www.etsy.com/listing/1849105234/personalized-wooden-iphone-apple-watch",
          "brand": {
            "@type": "Brand",
            "name": "Oakywood"
          },
          "offers": {
            "@type": "Offer",
            "price": "485.83",
            "priceCurrency": "BRL",
            "availability": "https://schema.org/InStock"
          }
        }
      },
      {
        "@type": "ListItem",
        "position": 26,
        "item": {
          "@type": "Product",
          "image": "https://i.etsystatic.com/13285848/r/il/c73d36/6360162196/il_fullxfull.6360162196_30wr.jpg",
          "name": "Handcrafted Oak Standing Desk: Adjustable Height Electric Computer Desk",
          "url": "https://www.etsy.com/listing/1797680330/handcrafted-oak-standing-desk-adjustable",
          "brand": {
            "@type": "Brand",
            "name": "Oakywood"
          },
          "offers": {
            "@type": "Offer",
            "price": "6012.14",
            "priceCurrency": "BRL",
            "availability": "https://schema.org/InStock"
          }
        }
      },
      {
        "@type": "ListItem",
        "position": 27,
        "item": {
          "@type": "Product",
          "image": "https://i.etsystatic.com/13285848/r/il/d4bb4d/4416393083/il_fullxfull.4416393083_dyiz.jpg",
          "name": "Merino Wool Felt & Cork Desk Mat: Large Home Office Pad",
          "url": "https://www.etsy.com/listing/847455636/merino-wool-felt-cork-desk-mat-large",
          "brand": {
            "@type": "Brand",
            "name": "Oakywood"
          },
          "offers": {
            "@type": "Offer",
            "price": "419.03",
            "priceCurrency": "BRL",
            "availability": "https://schema.org/InStock"
          }
        }
      },
      {
        "@type": "ListItem",
        "position": 28,
        "item": {
          "@type": "Product",
          "image": "https://i.etsystatic.com/13285848/r/il/cdc946/6408006711/il_fullxfull.6408006711_e9er.jpg",
          "name": "Solid Wood Standing Desk Pro Bundle: Adjustable Height Computer Desk",
          "url": "https://www.etsy.com/listing/1797631904/solid-wood-standing-desk-pro-bundle",
          "brand": {
            "@type": "Brand",
            "name": "Oakywood"
          },
          "offers": {
            "@type": "Offer",
            "price": "10153.84",
            "priceCurrency": "BRL",
            "availability": "https://schema.org/InStock"
          }
        }
      },
      {
        "@type": "ListItem",
        "position": 29,
        "item": {
          "@type": "Product",
          "image": "https://i.etsystatic.com/13285848/r/il/c36053/6359859674/il_fullxfull.6359859674_stal.jpg",
          "name": "Solid Wood Standing Desk Bundle: Adjustable Height, Cable Tray",
          "url": "https://www.etsy.com/listing/1797630272/solid-wood-standing-desk-bundle",
          "brand": {
            "@type": "Brand",
            "name": "Oakywood"
          },
          "offers": {
            "@type": "Offer",
            "price": "10153.84",
            "priceCurrency": "BRL",
            "availability": "https://schema.org/InStock"
          }
        }
      },
      {
        "@type": "ListItem",
        "position": 30,
        "item": {
          "@type": "Product",
          "image": "https://i.etsystatic.com/13285848/r/il/6338f2/4528672217/il_fullxfull.4528672217_i61k.jpg",
          "name": "2-in-1 Headphone Stand & Wireless Charger: Wooden Desk Organizer",
          "url": "https://www.etsy.com/listing/724454265/2-in-1-headphone-stand-wireless-charger",
          "brand": {
            "@type": "Brand",
            "name": "Oakywood"
          },
          "offers": {
            "@type": "Offer",
            "price": "546.56",
            "priceCurrency": "BRL",
            "availability": "https://schema.org/InStock"
          }
        }
      },
      {
        "@type": "ListItem",
        "position": 31,
        "item": {
          "@type": "Product",
          "image": "https://i.etsystatic.com/13285848/r/il/be3d1b/6959276613/il_fullxfull.6959276613_gwqw.jpg",
          "name": "Handcrafted Oakywood Floating Shelf: Solid Wood Wall Decor",
          "url": "https://www.etsy.com/listing/1766495820/handcrafted-oakywood-floating-shelf",
          "brand": {
            "@type": "Brand",
            "name": "Oakywood"
          },
          "offers": {
            "@type": "Offer",
            "price": "1396.76",
            "priceCurrency": "BRL",
            "availability": "https://schema.org/InStock"
          }
        }
      },
      {
        "@type": "ListItem",
        "position": 32,
        "item": {
          "@type": "Product",
          "image": "https://i.etsystatic.com/13285848/r/il/8bdbeb/5693026984/il_fullxfull.5693026984_stab.jpg",
          "name": "Ergonomic Wood Laptop Stand: Solid Wood Computer Holder",
          "url": "https://www.etsy.com/listing/529765307/ergonomic-wood-laptop-stand-solid-wood",
          "brand": {
            "@type": "Brand",
            "name": "Oakywood"
          },
          "offers": {
            "@type": "Offer",
            "price": "910.93",
            "priceCurrency": "BRL",
            "availability": "https://schema.org/InStock"
          }
        }
      },
      {
        "@type": "ListItem",
        "position": 33,
        "item": {
          "@type": "Product",
          "image": "https://i.etsystatic.com/13285848/r/il/53fcbe/6207727092/il_fullxfull.6207727092_99b2.jpg",
          "name": "Oakywood Electric Standing Desk: Solid Oak or Walnut Wood, White Legs",
          "url": "https://www.etsy.com/listing/1766487904/oakywood-electric-standing-desk-solid",
          "brand": {
            "@type": "Brand",
            "name": "Oakywood"
          },
          "offers": {
            "@type": "Offer",
            "price": "7226.72",
            "priceCurrency": "BRL",
            "availability": "https://schema.org/InStock"
          }
        }
      },
      {
        "@type": "ListItem",
        "position": 34,
        "item": {
          "@type": "Product",
          "image": "https://i.etsystatic.com/13285848/r/il/ea7b26/4369079578/il_fullxfull.4369079578_p74k.jpg",
          "name": "Dual Oak Laptop Stand: Vertical Macbook Dock, Desk Organizer",
          "url": "https://www.etsy.com/listing/949905096/dual-oak-laptop-stand-vertical-macbook",
          "brand": {
            "@type": "Brand",
            "name": "Oakywood"
          },
          "offers": {
            "@type": "Offer",
            "price": "485.83",
            "priceCurrency": "BRL",
            "availability": "https://schema.org/InStock"
          }
        }
      },
      {
        "@type": "ListItem",
        "position": 35,
        "item": {
          "@type": "Product",
          "image": "https://i.etsystatic.com/13285848/r/il/387fb0/5476129419/il_fullxfull.5476129419_snjk.jpg",
          "name": "Wooden MagSafe iPhone Stand: Ergonomic Charging Dock for iPhone 12-15",
          "url": "https://www.etsy.com/listing/1394459326/wooden-magsafe-iphone-stand-ergonomic",
          "brand": {
            "@type": "Brand",
            "name": "Oakywood"
          },
          "offers": {
            "@type": "Offer",
            "price": "910.93",
            "priceCurrency": "BRL",
            "availability": "https://schema.org/InStock"
          }
        }
      },
      {
        "@type": "ListItem",
        "position": 36,
        "item": {
          "@type": "Product",
          "image": "https://i.etsystatic.com/13285848/r/il/895501/6207728864/il_fullxfull.6207728864_aey3.jpg",
          "name": "Oakywood Handmade Solid Wood Standing Desk: Electric Adjustable Height",
          "url": "https://www.etsy.com/listing/1780667275/oakywood-handmade-solid-wood-standing",
          "brand": {
            "@type": "Brand",
            "name": "Oakywood"
          },
          "offers": {
            "@type": "Offer",
            "price": "7226.72",
            "priceCurrency": "BRL",
            "availability": "https://schema.org/InStock"
          }
        }
      }
    ],
    "numberOfItems": 110,
    "url": "https://www.etsy.com/shop/Oakywood"
  }
]